Metadata-Version: 1.0
Name: sdk-dominator
Version: 0.0.1
Summary: Reads and store user data to validate Sibyl Score
Home-page: https://github.com/rfschubert/sdk-dominator
Author: Raphael Schubert
Author-email: rfswdp@gmail.com
License:                     GNU GENERAL PUBLIC LICENSE
